{
  "decor": {
    "type": "generic",
    "width": 5.23,
    "height": 4.0,
    "depth": 4.75
  },
  "definitions": [
    {
      "subName": "",
      "modelName": "trophy_of_trinigaming_cowboycosmic",
      "name": "The Trophy Of Trinigaming - Cowboycosmic",
      "extraMaterials": []
    }
  ],
  "prefixFolders": "",
  "packID": "iv_tpp",
  "systemName": "trophy_of_trinigaming_cowboycosmic",
  "classification": "decor",
  "general": {
    "name": "The Trophy Of Trinigaming - Cowboycosmic",
    "materials": ["minecraft:gold_block:0:10","mts:iv_tcp_v3.trin_devom_substantial_firered_g:0:1"]
  }
}